CHANGELOG.txt
LICENCE.txt
MANIFEST.in
README.txt
setup.py
Sidfold/__init__.py
SidsFirstmod.egg-info/PKG-INFO
SidsFirstmod.egg-info/SOURCES.txt
SidsFirstmod.egg-info/dependency_links.txt
SidsFirstmod.egg-info/requires.txt
SidsFirstmod.egg-info/top_level.txt