Metadata-Version: 2.1
Name: SidsFirstmod
Version: 0.0.1
Summary: A funny module for trying out
Home-page: 
Author: Siddharth Narayanan
Author-email: siddharth1210@outlook.com
License: MIT
Keywords: Funny
Classifier: Development Status :: 5 - Production/Stable
Classifier: Intended Audience :: Education
Classifier: Operating System :: Microsoft :: Windows :: Windows 10
Classifier: License :: OSI Approved :: MIT License
Classifier: Programming Language :: Python :: 3
License-File: LICENCE.txt
